patchmatch_cython/__init__.py
patchmatch_cython/cython_solver.py
patchmatch_cython/cython_solver_impl.cp311-win_amd64.pyd
patchmatch_cython/cython_solver_impl.cpp
patchmatch_cython/cython_solver_impl.pyx
patchmatch_cython/imageops.py
patchmatch_cython/inpaint.py
patchmatch_cython/python_solver.py
patchmatch_cython/solver.py
patchmatch_cython-0.1.4.dist-info/licenses/LICENSE
patchmatch_cython-0.1.4.dist-info/METADATA
patchmatch_cython-0.1.4.dist-info/WHEEL
patchmatch_cython-0.1.4.dist-info/top_level.txt
patchmatch_cython-0.1.4.dist-info/RECORD
