Metadata-Version: 2.4
Name: patchmatch-cython
Version: 0.1.4
Summary: High-performance PatchMatch implementation for image inpainting using Cython
Home-page: https://github.com/Teriks/patchmatch-cython
Author: Teriks
Author-email: Teriks <Teriks999@gmail.com>
License: BSD 3-Clause License
Project-URL: Homepage, https://github.com/Teriks/patchmatch-cython
Project-URL: Repository, https://github.com/Teriks/patchmatch-cython
Project-URL: Issues, https://github.com/Teriks/patchmatch-cython/issues
Keywords: image-processing,inpainting,patchmatch,cython,computer-vision
Classifier: Development Status :: 4 - Beta
Classifier: Intended Audience :: Developers
Classifier: Intended Audience :: Science/Research
Classifier: Programming Language :: Python :: 3
Classifier: Programming Language :: Python :: 3.10
Classifier: Programming Language :: Python :: 3.11
Classifier: Programming Language :: Python :: 3.12
Classifier: Programming Language :: Python :: 3.13
Classifier: Programming Language :: Cython
Classifier: Topic :: Scientific/Engineering :: Image Processing
Classifier: Topic :: Scientific/Engineering :: Artificial Intelligence
Classifier: Topic :: Software Development :: Libraries :: Python Modules
Requires-Python: >=3.10
License-File: LICENSE
Requires-Dist: numpy>=1.21.0
Provides-Extra: visualization
Requires-Dist: matplotlib>=3.5.0; extra == "visualization"
Requires-Dist: Pillow>=8.0.0; extra == "visualization"
Provides-Extra: dev
Requires-Dist: pytest>=6.0.0; extra == "dev"
Requires-Dist: build>=0.8.0; extra == "dev"
Requires-Dist: setuptools>=61.0; extra == "dev"
Requires-Dist: wheel; extra == "dev"
Requires-Dist: Cython>=0.29.0; extra == "dev"
Dynamic: author
Dynamic: home-page
Dynamic: license-file
Dynamic: requires-python
